OpenSearchRec/__init__.py
OpenSearchRec/models/AlternatingLeastSquares.py
OpenSearchRec/models/__init__.py
OpenSearchRec/post_ranking/__init__.py
OpenSearchRec/post_ranking/centroids_selection.py
OpenSearchRec/post_ranking/list_merging.py
OpenSearchRec/retrieval/ElasticSearchRetrievalClient.py
OpenSearchRec/retrieval/OpenSearchRecRetrievalAPI.py
OpenSearchRec/retrieval/__init__.py
OpenSearchRec/retrieval/elasticsearch/__init__.py
OpenSearchRec/retrieval/elasticsearch/elasticsearch_query_utils.py
OpenSearchRec/retrieval/models/__init__.py
OpenSearchRec/retrieval/models/common.py
OpenSearchRec/retrieval/models/index.py
OpenSearchRec/retrieval/models/item.py
OpenSearchRec/retrieval/models/search.py
OpenSearchRec/utils/AsyncClassToSyncClassMetaClass.py
OpenSearchRec/utils/__init__.py
OpenSearchRec/utils/string_sanitization.py
tests/__init__.py
tests/post_ranking/__init__.py
tests/post_ranking/test_centroids_selection.py
tests/post_ranking/test_list_merging.py
tests/retrieval/__init__.py
tests/retrieval/test_search_item_model.py
tests/retrieval/test_with_elasticsearch_and_opensearch.py
OpenSearchRec-0.1.2.dist-info/LICENSE
OpenSearchRec-0.1.2.dist-info/METADATA
OpenSearchRec-0.1.2.dist-info/WHEEL
OpenSearchRec-0.1.2.dist-info/top_level.txt
OpenSearchRec-0.1.2.dist-info/RECORD
